DesmoothForecaster/__init__.py
DesmoothForecaster/main.py
DesmoothForecaster-0.4.1.dist-info/METADATA
DesmoothForecaster-0.4.1.dist-info/WHEEL
DesmoothForecaster-0.4.1.dist-info/top_level.txt
DesmoothForecaster-0.4.1.dist-info/RECORD
