Metadata-Version: 2.1
Name: DesmoothForecaster
Version: 0.4.1
Summary: Leveraging smoothing techniques to enhance time-series forecasting for difficult time-series data
Requires-Dist: numpy
Requires-Dist: pandas
Requires-Dist: statsmodels
Requires-Dist: tensorflow
Requires-Dist: scikit-learn
Requires-Dist: seaborn
Requires-Dist: matplotlib
